bk/__init__.py
bk/bk.py
bk/cli.py
pybk-0.1.0.dist-info/LICENSE
pybk-0.1.0.dist-info/METADATA
pybk-0.1.0.dist-info/WHEEL
pybk-0.1.0.dist-info/entry_points.txt
pybk-0.1.0.dist-info/top_level.txt
pybk-0.1.0.dist-info/RECORD
