Metadata-Version: 2.1
Name: pybk
Version: 0.1.0
Summary: Simple terminal app to manage bookmarks
Home-page: https://github.com/gmagno/bk
Author: Goncalo Magno
Author-email: goncalo.magno@gmail.com
License: MIT license
Keywords: bk
Platform: UNKNOWN
Classifier: Development Status :: 2 - Pre-Alpha
Classifier: Intended Audience :: Developers
Classifier: License :: OSI Approved :: MIT License
Classifier: Natural Language :: English
Classifier: Programming Language :: Python :: 3
Classifier: Programming Language :: Python :: 3.6
Classifier: Programming Language :: Python :: 3.7
Classifier: Programming Language :: Python :: 3.8
Requires-Python: >=3.6
Requires-Dist: Click (>=7.0)
